README.md
setup.py
tlimm/__init__.py
tlimm/process_image.py
tlimm/reader.py
tlimm/tlimm.py
tlimm/writer.py
tlimm.egg-info/PKG-INFO
tlimm.egg-info/SOURCES.txt
tlimm.egg-info/dependency_links.txt
tlimm.egg-info/requires.txt
tlimm.egg-info/top_level.txt